MANIFEST.in
README.md
setup.py
django_filtered_mail/__init__.py
django_filtered_mail/mail.py
django_filtered_mail/tests.py
django_filtered_mail.egg-info/PKG-INFO
django_filtered_mail.egg-info/SOURCES.txt
django_filtered_mail.egg-info/dependency_links.txt
django_filtered_mail.egg-info/not-zip-safe
django_filtered_mail.egg-info/requires.txt
django_filtered_mail.egg-info/top_level.txt