Metadata-Version: 1.1
Name: django-filtered-mail
Version: 0.2
Summary: Django Email Backend which only sends to whitelisted recipients
Home-page: https://github.com/rudolphfroger/django-filtered-mail
Author: Rudolph Froger
Author-email: rudolphfroger@dreamsolution.nl
License: MIT
Platform: UNKNOWN
Classifier: Development Status :: 3 - Alpha
Classifier: Environment :: Web Environment
Classifier: Intended Audience :: Developers
Classifier: License :: OSI Approved :: MIT License
Classifier: Operating System :: OS Independent
Classifier: Programming Language :: Python
Classifier: Framework :: Django
Classifier: Topic :: Communications :: Email :: Filters
